sanic_compress_plus/__init__.py
sanic_compress_plus-0.1.1.dist-info/LICENSE
sanic_compress_plus-0.1.1.dist-info/METADATA
sanic_compress_plus-0.1.1.dist-info/WHEEL
sanic_compress_plus-0.1.1.dist-info/top_level.txt
sanic_compress_plus-0.1.1.dist-info/RECORD
